znotify/__init__.py
znotify/client.py
znotify/send.py
znotify/static.py
znotify/version.py
znotify-0.4.0.dist-info/LICENSE
znotify-0.4.0.dist-info/WHEEL
znotify-0.4.0.dist-info/METADATA
znotify-0.4.0.dist-info/RECORD
